{
  "num_files": 125,
  "topk": 64,
  "top_features": [
    {
      "feature": 649,
      "delta": 1.5622178316116333
    },
    {
      "feature": 358,
      "delta": 1.5370928049087524
    },
    {
      "feature": 577,
      "delta": 1.51569402217865
    },
    {
      "feature": 400,
      "delta": 1.5041611194610596
    },
    {
      "feature": 212,
      "delta": 1.499932050704956
    },
    {
      "feature": 1121,
      "delta": 1.4778759479522705
    },
    {
      "feature": 1263,
      "delta": 1.4725916385650635
    },
    {
      "feature": 1136,
      "delta": 1.4509538412094116
    },
    {
      "feature": 549,
      "delta": 1.4395984411239624
    },
    {
      "feature": 787,
      "delta": 1.4383865594863892
    },
    {
      "feature": 360,
      "delta": 1.4332771301269531
    },
    {
      "feature": 250,
      "delta": 1.4327811002731323
    },
    {
      "feature": 1100,
      "delta": 1.398857593536377
    },
    {
      "feature": 1213,
      "delta": 1.3979218006134033
    },
    {
      "feature": 307,
      "delta": 1.3911786079406738
    },
    {
      "feature": 256,
      "delta": 1.3732976913452148
    },
    {
      "feature": 363,
      "delta": 1.3415340185165405
    },
    {
      "feature": 85,
      "delta": 1.3334650993347168
    },
    {
      "feature": 167,
      "delta": 1.331687569618225
    },
    {
      "feature": 583,
      "delta": 1.3271126747131348
    },
    {
      "feature": 1273,
      "delta": 1.3181027173995972
    },
    {
      "feature": 564,
      "delta": 1.3142863512039185
    },
    {
      "feature": 979,
      "delta": 1.3054437637329102
    },
    {
      "feature": 434,
      "delta": 1.2958157062530518
    },
    {
      "feature": 374,
      "delta": 1.2950347661972046
    },
    {
      "feature": 364,
      "delta": 1.2839646339416504
    },
    {
      "feature": 1132,
      "delta": 1.2712863683700562
    },
    {
      "feature": 1012,
      "delta": 1.2529737949371338
    },
    {
      "feature": 107,
      "delta": 1.2332271337509155
    },
    {
      "feature": 1082,
      "delta": 1.2286041975021362
    },
    {
      "feature": 641,
      "delta": 1.227664589881897
    },
    {
      "feature": 193,
      "delta": 1.2122246026992798
    },
    {
      "feature": 383,
      "delta": 1.2082377672195435
    },
    {
      "feature": 608,
      "delta": 1.1928155422210693
    },
    {
      "feature": 387,
      "delta": 1.1861249208450317
    },
    {
      "feature": 481,
      "delta": 1.163443684577942
    },
    {
      "feature": 273,
      "delta": 1.1497858762741089
    },
    {
      "feature": 1218,
      "delta": 1.092057228088379
    },
    {
      "feature": 435,
      "delta": 1.067284345626831
    },
    {
      "feature": 857,
      "delta": 1.0407178401947021
    },
    {
      "feature": 1170,
      "delta": 1.0392036437988281
    },
    {
      "feature": 70,
      "delta": 1.0169144868850708
    },
    {
      "feature": 1169,
      "delta": 1.000686764717102
    },
    {
      "feature": 113,
      "delta": 0.9623079895973206
    },
    {
      "feature": 528,
      "delta": 0.9495225548744202
    },
    {
      "feature": 507,
      "delta": 0.9404307007789612
    },
    {
      "feature": 1190,
      "delta": 0.8930529952049255
    },
    {
      "feature": 949,
      "delta": 0.8822080492973328
    },
    {
      "feature": 696,
      "delta": 0.8607338070869446
    },
    {
      "feature": 218,
      "delta": 0.7906700968742371
    },
    {
      "feature": 926,
      "delta": 0.7606483101844788
    },
    {
      "feature": 993,
      "delta": 0.7342327833175659
    },
    {
      "feature": 1250,
      "delta": 0.7223197817802429
    },
    {
      "feature": 242,
      "delta": 0.7165667414665222
    },
    {
      "feature": 4,
      "delta": 0.7084761261940002
    },
    {
      "feature": 563,
      "delta": 0.6875805258750916
    },
    {
      "feature": 166,
      "delta": 0.6713430881500244
    },
    {
      "feature": 590,
      "delta": 0.6641084551811218
    },
    {
      "feature": 755,
      "delta": 0.6528056859970093
    },
    {
      "feature": 49,
      "delta": 0.5739468336105347
    },
    {
      "feature": 1178,
      "delta": 0.5698590278625488
    },
    {
      "feature": 416,
      "delta": 0.4165711998939514
    },
    {
      "feature": 384,
      "delta": 0.40386059880256653
    },
    {
      "feature": 905,
      "delta": 0.4004698693752289
    }
  ]
}